{
    "Ar36": {
        "error": 0.00021405384326973536,
        "error_type": "SEM",
        "filter_outliers_dict": {
            "filter_outliers": true,
            "iterations": 1,
            "std_devs": 2
        },
        "fit": "linear",
        "value": 0.01677804405573051
    },
    "Ar37": {
        "error": 0.0036256138371008606,
        "error_type": "SEM",
        "filter_outliers_dict": {
            "filter_outliers": true,
            "iterations": 1,
            "std_devs": 2
        },
        "fit": "linear",
        "value": 1.109892755542583
    },
    "Ar38": {
        "error": 0.0033310637217626913,
        "error_type": "SEM",
        "filter_outliers_dict": {
            "filter_outliers": true,
            "iterations": 1,
            "std_devs": 2
        },
        "fit": "linear",
        "value": 4.294953641033711
    },
    "Ar39": {
        "error": 0.035297197715650534,
        "error_type": "SEM",
        "filter_outliers_dict": {
            "filter_outliers": true,
            "iterations": 1,
            "std_devs": 2
        },
        "fit": "Parabolic",
        "value": 343.8942562094816
    },
    "Ar40": {
        "error": 0.08131503569118763,
        "error_type": "SEM",
        "filter_outliers_dict": {
            "filter_outliers": true,
            "iterations": 1,
            "std_devs": 3
        },
        "fit": "Parabolic",
        "value": 1507.6683419853834
    },
    "Ar41": {
        "error": 0.01545377377640924,
        "error_type": "SEM",
        "filter_outliers_dict": {
            "filter_outliers": true,
            "iterations": 1,
            "std_devs": 3
        },
        "fit": "average",
        "value": -0.21852964048370419
    }
}