{
    "Ar36": {
        "error": 0.0002701696622151443,
        "error_type": "SEM",
        "filter_outliers_dict": {
            "filter_outliers": true,
            "iterations": 1,
            "std_devs": 3,
            "use_iqr_filtering": false,
            "use_standard_deviation_filtering": false
        },
        "fit": "linear",
        "fn": 278,
        "include_baseline_error": true,
        "n": 280,
        "outlier_excluded": [
            0,
            8
        ],
        "reviewed": true,
        "user_excluded": [],
        "value": 0.01965496844891064
    },
    "Ar37": {
        "error": 0.004093096187897788,
        "error_type": "SEM",
        "filter_outliers_dict": {
            "filter_outliers": true,
            "iterations": 1,
            "std_devs": 3,
            "use_iqr_filtering": false,
            "use_standard_deviation_filtering": false
        },
        "fit": "linear",
        "fn": 279,
        "include_baseline_error": true,
        "n": 280,
        "outlier_excluded": [
            29
        ],
        "reviewed": true,
        "user_excluded": [],
        "value": 0.584848410714359
    },
    "Ar38": {
        "error": 0.0034096253694933195,
        "error_type": "SEM",
        "filter_outliers_dict": {
            "filter_outliers": true,
            "iterations": 1,
            "std_devs": 3,
            "use_iqr_filtering": false,
            "use_standard_deviation_filtering": false
        },
        "fit": "linear",
        "fn": 278,
        "include_baseline_error": true,
        "n": 280,
        "outlier_excluded": [
            0,
            86
        ],
        "reviewed": true,
        "user_excluded": [],
        "value": 0.8031311328234709
    },
    "Ar39": {
        "error": 0.020779465578712252,
        "error_type": "SEM",
        "filter_outliers_dict": {
            "filter_outliers": true,
            "iterations": 1,
            "std_devs": 3,
            "use_iqr_filtering": false,
            "use_standard_deviation_filtering": false
        },
        "fit": "parabolic",
        "fn": 280,
        "include_baseline_error": true,
        "n": 280,
        "outlier_excluded": [],
        "reviewed": true,
        "user_excluded": [],
        "value": 61.43019543156566
    },
    "Ar40": {
        "error": 0.031769051189148315,
        "error_type": "SEM",
        "filter_outliers_dict": {
            "filter_outliers": true,
            "iterations": 1,
            "std_devs": 3,
            "use_iqr_filtering": false,
            "use_standard_deviation_filtering": false
        },
        "fit": "parabolic",
        "fn": 280,
        "include_baseline_error": true,
        "n": 280,
        "outlier_excluded": [],
        "reviewed": true,
        "user_excluded": [],
        "value": 274.00813293095007
    },
    "Ar41": {
        "error": 0.017038505583247557,
        "error_type": "SEM",
        "filter_outliers_dict": {
            "filter_outliers": true,
            "iterations": 1,
            "std_devs": 3
        },
        "fit": "average",
        "value": -0.19470821645067102
    }
}